LICENSE
MANIFEST.in
README.md
requirements.txt
setup.cfg
setup.py
midpoint_cli.egg-info/PKG-INFO
midpoint_cli.egg-info/SOURCES.txt
midpoint_cli.egg-info/dependency_links.txt
midpoint_cli.egg-info/requires.txt
midpoint_cli.egg-info/top_level.txt
src/midpoint-cli
src/midpoint_cli/__init__.py
src/midpoint_cli/client/__init__.py
src/midpoint_cli/client/objects.py
src/midpoint_cli/client/observer.py
src/midpoint_cli/client/patch.py
src/midpoint_cli/client/progress.py
src/midpoint_cli/client/session.py
src/midpoint_cli/prompt/__init__.py
src/midpoint_cli/prompt/base.py
src/midpoint_cli/prompt/complete.py
src/midpoint_cli/prompt/configuration.py
src/midpoint_cli/prompt/console.py
src/midpoint_cli/prompt/delete.py
src/midpoint_cli/prompt/get.py
src/midpoint_cli/prompt/org.py
src/midpoint_cli/prompt/put.py
src/midpoint_cli/prompt/resource.py
src/midpoint_cli/prompt/script.py
src/midpoint_cli/prompt/task.py
src/midpoint_cli/prompt/user.py
test/test_client_api.py
test/test_client_model.py
test/test_client_put.py
test/test_environment.py
test/test_parser.py
test/test_patch.py
test/test_script.py