Metadata-Version: 2.1
Name: midpoint-cli
Version: 1.3.1
Summary: A command line client to Midpoint Identity Management system.
Home-page: https://gitlab.com/alcibiade/midpoint-cli
Author: Yannick Kirschhoffer
Author-email: alcibiade@alcibiade.org
License: MIT
Classifier: Development Status :: 5 - Production/Stable
Classifier: Intended Audience :: Developers
Classifier: Intended Audience :: System Administrators
Classifier: Topic :: System :: Systems Administration
Classifier: License :: OSI Approved :: MIT License
Classifier: Programming Language :: Python :: 3
License-File: LICENSE
Requires-Dist: clint>=0.5
Requires-Dist: tabulate>=0.9
Requires-Dist: unidecode>=1.3
Requires-Dist: requests>=2.31
Requires-Dist: urllib3>=2.0
Requires-Dist: setuptools>=68.0
